Metadata-Version: 2.1
Name: auto-emailer
Version: 1.0.1
Summary: auto-emailer library for Python
Home-page: https://github.com/adamstueckrath/auto-emailer
Author: Adam Stueckrath
Author-email: stueckrath.adam@gmail.com
License: MIT
Keywords: smtp email
Platform: UNKNOWN
Classifier: Development Status :: 3 - Alpha
Classifier: Intended Audience :: Developers
Classifier: Topic :: Software Development :: Libraries :: Python Modules
Classifier: License :: OSI Approved :: MIT License
Classifier: Programming Language :: Python :: 3.6
Classifier: Programming Language :: Python :: 3.7
